jalali_calendar_qt/__init__.py
jalali_calendar_qt/__version__.py
jalali_calendar_qt/date_edit.py
jalali_calendar_qt/datepicker.py
jalali_calendar_qt/datetime_edit.py
jalali_calendar_qt/time_edit.py
jalali_calendar_qt/timepicker.py
jalali_calendar_qt/utils.py
jalali_calendar_qt/assets/BNazanin.ttf
jalali_calendar_qt/assets/calendar-black.svg
jalali_calendar_qt/assets/calendar-white.svg
jalali_calendar_qt/assets/clock-black.svg
jalali_calendar_qt/assets/clock-white.svg
jalali_calendar_qt-1.1.0.dist-info/licenses/LICENSE
jalali_calendar_qt-1.1.0.dist-info/METADATA
jalali_calendar_qt-1.1.0.dist-info/WHEEL
jalali_calendar_qt-1.1.0.dist-info/top_level.txt
jalali_calendar_qt-1.1.0.dist-info/RECORD
