Metadata-Version: 2.4
Name: jalali-calendar-qt
Version: 1.1.0
Summary: A companion library providing themeable and scalable Qt (PySide6) widgets for the persian-jalali-calendar library.
Author-email: "Hamid R. Yari" <hryarih@gmail.com>
License: MIT License
Project-URL: Homepage, https://github.com/hryarih32/jalali-calendar-qt
Project-URL: Bug Tracker, https://github.com/hryarih32/jalali-calendar-qt/issues
Keywords: jalali,persian,calendar,shamsi,qt,pyside,datepicker,timepicker,gui
Classifier: Development Status :: 5 - Production/Stable
Classifier: Intended Audience :: Developers
Classifier: Topic :: Software Development :: Libraries :: Python Modules
Classifier: Topic :: Software Development :: User Interfaces
Classifier: Topic :: Software Development :: Widget Sets
Classifier: License :: OSI Approved :: MIT License
Classifier: Programming Language :: Python :: 3
Classifier: Programming Language :: Python :: 3.8
Classifier: Programming Language :: Python :: 3.9
Classifier: Programming Language :: Python :: 3.10
Classifier: Programming Language :: Python :: 3.11
Classifier: Programming Language :: Python :: 3.12
Classifier: Operating System :: OS Independent
Requires-Python: >=3.7
License-File: LICENSE
Requires-Dist: persian-jalali-calendar>=1.1.0
Requires-Dist: PySide6
Dynamic: license-file
